{"config":{"output_file":null,"full_docs":false,"pub_only":true,"reachable_only":true,"distro_crate":false,"signatures":false,"borrow_data":false},"version":"0.19.0","compilation":{"directory":"C:\\Users\\12935\\.cargo\\registry\\src\\mirrors.ustc.edu.cn-b63e9dae659fc205\\vcpkg-0.2.10","program":"C:\\Users\\12935\\.rustup\\toolchains\\stable-x86_64-pc-windows-msvc\\bin\\rls.exe","arguments":["--crate-name","vcpkg","C:\\Users\\12935\\.cargo\\registry\\src\\mirrors.ustc.edu.cn-b63e9dae659fc205\\vcpkg-0.2.10\\src\\lib.rs","--json=diagnostic-rendered-ansi","--crate-type","lib","--emit=dep-info,metadata,link","-C","debuginfo=2","-C","metadata=1ead9e759780da0c","-C","extra-filename=-1ead9e759780da0c","--out-dir","e:\\STUDY\\GKD\\GKD\\codes\\web工程\\backend\\target\\rls\\debug\\deps","-L","dependency=e:\\STUDY\\GKD\\GKD\\codes\\web工程\\backend\\target\\rls\\debug\\deps","--cap-lints","allow","--error-format=json","--sysroot","C:\\Users\\12935\\.rustup/toolchains/stable-x86_64-pc-windows-msvc"],"output":"e:\\STUDY\\GKD\\GKD\\codes\\web工程\\backend\\target\\rls\\debug\\deps\\libvcpkg-1ead9e759780da0c.rmeta"},"prelude":{"crate_id":{"name":"vcpkg","disambiguator":[7089666465968308197,17337954640709282740]},"crate_root":"C:\\Users\\12935\\.cargo\\registry\\src\\mirrors.ustc.edu.cn-b63e9dae659fc205\\vcpkg-0.2.10\\src","external_crates":[{"file_name":"C:\\Users\\12935\\.cargo\\registry\\src\\mirrors.ustc.edu.cn-b63e9dae659fc205\\vcpkg-0.2.10\\src\\lib.rs","num":1,"id":{"name":"std","disambiguator":[2953284957370121905,516218847044108999]}},{"file_name":"C:\\Users\\12935\\.cargo\\registry\\src\\mirrors.ustc.edu.cn-b63e9dae659fc205\\vcpkg-0.2.10\\src\\lib.rs","num":2,"id":{"name":"core","disambiguator":[4886921161452974022,9452701908620647308]}},{"file_name":"C:\\Users\\12935\\.cargo\\registry\\src\\mirrors.ustc.edu.cn-b63e9dae659fc205\\vcpkg-0.2.10\\src\\lib.rs","num":3,"id":{"name":"compiler_builtins","disambiguator":[3203561457090851205,4632072058037203867]}},{"file_name":"C:\\Users\\12935\\.cargo\\registry\\src\\mirrors.ustc.edu.cn-b63e9dae659fc205\\vcpkg-0.2.10\\src\\lib.rs","num":4,"id":{"name":"rustc_std_workspace_core","disambiguator":[3169376498131592849,9803978538207206865]}},{"file_name":"C:\\Users\\12935\\.cargo\\registry\\src\\mirrors.ustc.edu.cn-b63e9dae659fc205\\vcpkg-0.2.10\\src\\lib.rs","num":5,"id":{"name":"alloc","disambiguator":[9199649512872691809,295485750221223515]}},{"file_name":"C:\\Users\\12935\\.cargo\\registry\\src\\mirrors.ustc.edu.cn-b63e9dae659fc205\\vcpkg-0.2.10\\src\\lib.rs","num":6,"id":{"name":"libc","disambiguator":[8443236399884245798,5222098755004489868]}},{"file_name":"C:\\Users\\12935\\.cargo\\registry\\src\\mirrors.ustc.edu.cn-b63e9dae659fc205\\vcpkg-0.2.10\\src\\lib.rs","num":7,"id":{"name":"unwind","disambiguator":[6875631416372754603,10839808870381595949]}},{"file_name":"C:\\Users\\12935\\.cargo\\registry\\src\\mirrors.ustc.edu.cn-b63e9dae659fc205\\vcpkg-0.2.10\\src\\lib.rs","num":8,"id":{"name":"cfg_if","disambiguator":[1502820548942319655,12324332090615114041]}},{"file_name":"C:\\Users\\12935\\.cargo\\registry\\src\\mirrors.ustc.edu.cn-b63e9dae659fc205\\vcpkg-0.2.10\\src\\lib.rs","num":9,"id":{"name":"backtrace","disambiguator":[430706850608609257,9838809896428719127]}},{"file_name":"C:\\Users\\12935\\.cargo\\registry\\src\\mirrors.ustc.edu.cn-b63e9dae659fc205\\vcpkg-0.2.10\\src\\lib.rs","num":10,"id":{"name":"rustc_demangle","disambiguator":[14503357713055743246,17731918345561731946]}},{"file_name":"C:\\Users\\12935\\.cargo\\registry\\src\\mirrors.ustc.edu.cn-b63e9dae659fc205\\vcpkg-0.2.10\\src\\lib.rs","num":11,"id":{"name":"hashbrown","disambiguator":[5693586899772496405,17220236988479499600]}},{"file_name":"C:\\Users\\12935\\.cargo\\registry\\src\\mirrors.ustc.edu.cn-b63e9dae659fc205\\vcpkg-0.2.10\\src\\lib.rs","num":12,"id":{"name":"rustc_std_workspace_alloc","disambiguator":[1060170945230123807,4750192540160149325]}},{"file_name":"C:\\Users\\12935\\.cargo\\registry\\src\\mirrors.ustc.edu.cn-b63e9dae659fc205\\vcpkg-0.2.10\\src\\lib.rs","num":13,"id":{"name":"panic_unwind","disambiguator":[5837979218880944404,14867613958503134191]}}],"span":{"file_name":"C:\\Users\\12935\\.cargo\\registry\\src\\mirrors.ustc.edu.cn-b63e9dae659fc205\\vcpkg-0.2.10\\src\\lib.rs","byte_start":0,"byte_end":49361,"line_start":1,"line_end":1387,"column_start":1,"column_end":2}},"imports":[],"defs":[{"kind":"Mod","id":{"krate":0,"index":0},"span":{"file_name":"C:\\Users\\12935\\.cargo\\registry\\src\\mirrors.ustc.edu.cn-b63e9dae659fc205\\vcpkg-0.2.10\\src\\lib.rs","byte_start":0,"byte_end":49361,"line_start":1,"line_end":1387,"column_start":1,"column_end":2},"name":"","qualname":"::","value":"C:\\Users\\12935\\.cargo\\registry\\src\\mirrors.ustc.edu.cn-b63e9dae659fc205\\vcpkg-0.2.10\\src\\lib.rs","parent":null,"children":[{"krate":0,"index":1},{"krate":0,"index":2},{"krate":0,"index":3},{"krate":0,"index":4},{"krate":0,"index":5},{"krate":0,"index":6},{"krate":0,"index":7},{"krate":0,"index":8},{"krate":0,"index":9},{"krate":0,"index":12},{"krate":0,"index":15},{"krate":0,"index":73},{"krate":0,"index":80},{"krate":0,"index":82},{"krate":0,"index":92},{"krate":0,"index":18},{"krate":0,"index":94},{"krate":0,"index":114},{"krate":0,"index":23},{"krate":0,"index":26},{"krate":0,"index":28},{"krate":0,"index":29},{"krate":0,"index":30},{"krate":0,"index":31},{"krate":0,"index":32},{"krate":0,"index":117},{"krate":0,"index":123},{"krate":0,"index":121},{"krate":0,"index":33},{"krate":0,"index":35},{"krate":0,"index":36},{"krate":0,"index":38},{"krate":0,"index":47},{"krate":0,"index":51},{"krate":0,"index":65},{"krate":0,"index":67},{"krate":0,"index":69},{"krate":0,"index":72}],"decl_id":null,"docs":" A build dependency for Cargo libraries to find libraries in a\n [Vcpkg](https://github.com/microsoft/vcpkg) tree","sig":null,"attributes":[{"value":"! A build dependency for Cargo libraries to find libraries in a","span":{"file_name":"C:\\Users\\12935\\.cargo\\registry\\src\\mirrors.ustc.edu.cn-b63e9dae659fc205\\vcpkg-0.2.10\\src\\lib.rs","byte_start":0,"byte_end":65,"line_start":1,"line_end":1,"column_start":1,"column_end":66}},{"value":"! [Vcpkg](https://github.com/microsoft/vcpkg) tree","span":{"file_name":"C:\\Users\\12935\\.cargo\\registry\\src\\mirrors.ustc.edu.cn-b63e9dae659fc205\\vcpkg-0.2.10\\src\\lib.rs","byte_start":66,"byte_end":118,"line_start":2,"line_end":2,"column_start":1,"column_end":53}},{"value":"!","span":{"file_name":"C:\\Users\\12935\\.cargo\\registry\\src\\mirrors.ustc.edu.cn-b63e9dae659fc205\\vcpkg-0.2.10\\src\\lib.rs","byte_start":119,"byte_end":122,"line_start":3,"line_end":3,"column_start":1,"column_end":4}},{"value":"! From a Vcpkg package name","span":{"file_name":"C:\\Users\\12935\\.cargo\\registry\\src\\mirrors.ustc.edu.cn-b63e9dae659fc205\\vcpkg-0.2.10\\src\\lib.rs","byte_start":123,"byte_end":152,"line_start":4,"line_end":4,"column_start":1,"column_end":30}},{"value":"! this build helper will emit cargo metadata to link it and it's dependencies","span":{"file_name":"C:\\Users\\12935\\.cargo\\registry\\src\\mirrors.ustc.edu.cn-b63e9dae659fc205\\vcpkg-0.2.10\\src\\lib.rs","byte_start":153,"byte_end":232,"line_start":5,"line_end":5,"column_start":1,"column_end":80}},{"value":"! (excluding system libraries, which it does not determine).","span":{"file_name":"C:\\Users\\12935\\.cargo\\registry\\src\\mirrors.ustc.edu.cn-b63e9dae659fc205\\vcpkg-0.2.10\\src\\lib.rs","byte_start":233,"byte_end":295,"line_start":6,"line_end":6,"column_start":1,"column_end":63}},{"value":"!","span":{"file_name":"C:\\Users\\12935\\.cargo\\registry\\src\\mirrors.ustc.edu.cn-b63e9dae659fc205\\vcpkg-0.2.10\\src\\lib.rs","byte_start":296,"byte_end":299,"line_start":7,"line_end":7,"column_start":1,"column_end":4}},{"value":"! The simplest possible usage looks like this :-","span":{"file_name":"C:\\Users\\12935\\.cargo\\registry\\src\\mirrors.ustc.edu.cn-b63e9dae659fc205\\vcpkg-0.2.10\\src\\lib.rs","byte_start":300,"byte_end":350,"line_start":8,"line_end":8,"column_start":1,"column_end":51}},{"value":"!","span":{"file_name":"C:\\Users\\12935\\.cargo\\registry\\src\\mirrors.ustc.edu.cn-b63e9dae659fc205\\vcpkg-0.2.10\\src\\lib.rs","byte_start":351,"byte_end":354,"line_start":9,"line_end":9,"column_start":1,"column_end":4}},{"value":"! ```rust,no_run","span":{"file_name":"C:\\Users\\12935\\.cargo\\registry\\src\\mirrors.ustc.edu.cn-b63e9dae659fc205\\vcpkg-0.2.10\\src\\lib.rs","byte_start":355,"byte_end":373,"line_start":10,"line_end":10,"column_start":1,"column_end":19}},{"value":"! vcpkg::find_package(\"libssh2\").unwrap();","span":{"file_name":"C:\\Users\\12935\\.cargo\\registry\\src\\mirrors.ustc.edu.cn-b63e9dae659fc205\\vcpkg-0.2.10\\src\\lib.rs","byte_start":374,"byte_end":418,"line_start":11,"line_end":11,"column_start":1,"column_end":45}},{"value":"! ```","span":{"file_name":"C:\\Users\\12935\\.cargo\\registry\\src\\mirrors.ustc.edu.cn-b63e9dae659fc205\\vcpkg-0.2.10\\src\\lib.rs","byte_start":419,"byte_end":426,"line_start":12,"line_end":12,"column_start":1,"column_end":8}},{"value":"!","span":{"file_name":"C:\\Users\\12935\\.cargo\\registry\\src\\mirrors.ustc.edu.cn-b63e9dae659fc205\\vcpkg-0.2.10\\src\\lib.rs","byte_start":427,"byte_end":430,"line_start":13,"line_end":13,"column_start":1,"column_end":4}},{"value":"! The cargo metadata that is emitted can be changed like this :-","span":{"file_name":"C:\\Users\\12935\\.cargo\\registry\\src\\mirrors.ustc.edu.cn-b63e9dae659fc205\\vcpkg-0.2.10\\src\\lib.rs","byte_start":431,"byte_end":497,"line_start":14,"line_end":14,"column_start":1,"column_end":67}},{"value":"!","span":{"file_name":"C:\\Users\\12935\\.cargo\\registry\\src\\mirrors.ustc.edu.cn-b63e9dae659fc205\\vcpkg-0.2.10\\src\\lib.rs","byte_start":498,"byte_end":501,"line_start":15,"line_end":15,"column_start":1,"column_end":4}},{"value":"! ```rust,no_run","span":{"file_name":"C:\\Users\\12935\\.cargo\\registry\\src\\mirrors.ustc.edu.cn-b63e9dae659fc205\\vcpkg-0.2.10\\src\\lib.rs","byte_start":502,"byte_end":520,"line_start":16,"line_end":16,"column_start":1,"column_end":19}},{"value":"! vcpkg::Config::new()","span":{"file_name":"C:\\Users\\12935\\.cargo\\registry\\src\\mirrors.ustc.edu.cn-b63e9dae659fc205\\vcpkg-0.2.10\\src\\lib.rs","byte_start":521,"byte_end":545,"line_start":17,"line_end":17,"column_start":1,"column_end":25}},{"value":"!     .emit_includes(true)","span":{"file_name":"C:\\Users\\12935\\.cargo\\registry\\src\\mirrors.ustc.edu.cn-b63e9dae659fc205\\vcpkg-0.2.10\\src\\lib.rs","byte_start":546,"byte_end":574,"line_start":18,"line_end":18,"column_start":1,"column_end":29}},{"value":"!     .find_package(\"zlib\").unwrap();","span":{"file_name":"C:\\Users\\12935\\.cargo\\registry\\src\\mirrors.ustc.edu.cn-b63e9dae659fc205\\vcpkg-0.2.10\\src\\lib.rs","byte_start":575,"byte_end":614,"line_start":19,"line_end":19,"column_start":1,"column_end":40}},{"value":"! ```","span":{"file_name":"C:\\Users\\12935\\.cargo\\registry\\src\\mirrors.ustc.edu.cn-b63e9dae659fc205\\vcpkg-0.2.10\\src\\lib.rs","byte_start":615,"byte_end":622,"line_start":20,"line_end":20,"column_start":1,"column_end":8}},{"value":"!","span":{"file_name":"C:\\Users\\12935\\.cargo\\registry\\src\\mirrors.ustc.edu.cn-b63e9dae659fc205\\vcpkg-0.2.10\\src\\lib.rs","byte_start":623,"byte_end":626,"line_start":21,"line_end":21,"column_start":1,"column_end":4}},{"value":"! If the search was successful all appropriate Cargo metadata will be printed","span":{"file_name":"C:\\Users\\12935\\.cargo\\registry\\src\\mirrors.ustc.edu.cn-b63e9dae659fc205\\vcpkg-0.2.10\\src\\lib.rs","byte_start":627,"byte_end":706,"line_start":22,"line_end":22,"column_start":1,"column_end":80}},{"value":"! to stdout.","span":{"file_name":"C:\\Users\\12935\\.cargo\\registry\\src\\mirrors.ustc.edu.cn-b63e9dae659fc205\\vcpkg-0.2.10\\src\\lib.rs","byte_start":707,"byte_end":721,"line_start":23,"line_end":23,"column_start":1,"column_end":15}},{"value":"!","span":{"file_name":"C:\\Users\\12935\\.cargo\\registry\\src\\mirrors.ustc.edu.cn-b63e9dae659fc205\\vcpkg-0.2.10\\src\\lib.rs","byte_start":722,"byte_end":725,"line_start":24,"line_end":24,"column_start":1,"column_end":4}},{"value":"! ## Static vs. dynamic linking","span":{"file_name":"C:\\Users\\12935\\.cargo\\registry\\src\\mirrors.ustc.edu.cn-b63e9dae659fc205\\vcpkg-0.2.10\\src\\lib.rs","byte_start":726,"byte_end":759,"line_start":25,"line_end":25,"column_start":1,"column_end":34}},{"value":"! At this time, vcpkg itself only has a single triplet on macOS and Linux which builds","span":{"file_name":"C:\\Users\\12935\\.cargo\\registry\\src\\mirrors.ustc.edu.cn-b63e9dae659fc205\\vcpkg-0.2.10\\src\\lib.rs","byte_start":760,"byte_end":848,"line_start":26,"line_end":26,"column_start":1,"column_end":89}},{"value":"! static link versions of libraries, which works well with Rust.","span":{"file_name":"C:\\Users\\12935\\.cargo\\registry\\src\\mirrors.ustc.edu.cn-b63e9dae659fc205\\vcpkg-0.2.10\\src\\lib.rs","byte_start":849,"byte_end":915,"line_start":27,"line_end":27,"column_start":1,"column_end":67}},{"value":"! On Windows there are three","span":{"file_name":"C:\\Users\\12935\\.cargo\\registry\\src\\mirrors.ustc.edu.cn-b63e9dae659fc205\\vcpkg-0.2.10\\src\\lib.rs","byte_start":916,"byte_end":946,"line_start":28,"line_end":28,"column_start":1,"column_end":31}},{"value":"! configurations that are supported for 64-bit builds and another three for 32-bit.","span":{"file_name":"C:\\Users\\12935\\.cargo\\registry\\src\\mirrors.ustc.edu.cn-b63e9dae659fc205\\vcpkg-0.2.10\\src\\lib.rs","byte_start":947,"byte_end":1032,"line_start":29,"line_end":29,"column_start":1,"column_end":86}},{"value":"! The default 64-bit configuration is `x64-windows-static-md` which is a","span":{"file_name":"C:\\Users\\12935\\.cargo\\registry\\src\\mirrors.ustc.edu.cn-b63e9dae659fc205\\vcpkg-0.2.10\\src\\lib.rs","byte_start":1033,"byte_end":1107,"line_start":30,"line_end":30,"column_start":1,"column_end":75}},{"value":"! [community supported](https://github.com/microsoft/vcpkg/blob/master/docs/users/triplets.md#community-triplets)","span":{"file_name":"C:\\Users\\12935\\.cargo\\registry\\src\\mirrors.ustc.edu.cn-b63e9dae659fc205\\vcpkg-0.2.10\\src\\lib.rs","byte_start":1108,"byte_end":1223,"line_start":31,"line_end":31,"column_start":1,"column_end":116}},{"value":"! configuration that is a good match for Rust - dynamically linking to the C runtime,","span":{"file_name":"C:\\Users\\12935\\.cargo\\registry\\src\\mirrors.ustc.edu.cn-b63e9dae659fc205\\vcpkg-0.2.10\\src\\lib.rs","byte_start":1224,"byte_end":1311,"line_start":32,"line_end":32,"column_start":1,"column_end":88}},{"value":"! and statically linking to the packages in vcpkg. Another option is to build a fully static","span":{"file_name":"C:\\Users\\12935\\.cargo\\registry\\src\\mirrors.ustc.edu.cn-b63e9dae659fc205\\vcpkg-0.2.10\\src\\lib.rs","byte_start":1312,"byte_end":1406,"line_start":33,"line_end":33,"column_start":1,"column_end":95}},{"value":"! binary using `RUSTFLAGS=-Ctarget-feature=+crt-static`. This will link to libraries built","span":{"file_name":"C:\\Users\\12935\\.cargo\\registry\\src\\mirrors.ustc.edu.cn-b63e9dae659fc205\\vcpkg-0.2.10\\src\\lib.rs","byte_start":1407,"byte_end":1499,"line_start":34,"line_end":34,"column_start":1,"column_end":93}},{"value":"! with vcpkg triplet `x64-windows-static`. For dynamic linking, set `VCPKGRS_DYNAMIC=1` in the","span":{"file_name":"C:\\Users\\12935\\.cargo\\registry\\src\\mirrors.ustc.edu.cn-b63e9dae659fc205\\vcpkg-0.2.10\\src\\lib.rs","byte_start":1500,"byte_end":1596,"line_start":35,"line_end":35,"column_start":1,"column_end":97}},{"value":"! environment. This will link to libraries built with vcpkg triplet `x64-windows`. If `VCPKGRS_DYNAMIC` is set, `cargo install` will","span":{"file_name":"C:\\Users\\12935\\.cargo\\registry\\src\\mirrors.ustc.edu.cn-b63e9dae659fc205\\vcpkg-0.2.10\\src\\lib.rs","byte_start":1597,"byte_end":1731,"line_start":36,"line_end":36,"column_start":1,"column_end":135}},{"value":"! generate dynamically linked binaries, in which case you will have to arrange for","span":{"file_name":"C:\\Users\\12935\\.cargo\\registry\\src\\mirrors.ustc.edu.cn-b63e9dae659fc205\\vcpkg-0.2.10\\src\\lib.rs","byte_start":1732,"byte_end":1816,"line_start":37,"line_end":37,"column_start":1,"column_end":85}},{"value":"! dlls from your Vcpkg installation to be available in your path.","span":{"file_name":"C:\\Users\\12935\\.cargo\\registry\\src\\mirrors.ustc.edu.cn-b63e9dae659fc205\\vcpkg-0.2.10\\src\\lib.rs","byte_start":1817,"byte_end":1884,"line_start":38,"line_end":38,"column_start":1,"column_end":68}},{"value":"!","span":{"file_name":"C:\\Users\\12935\\.cargo\\registry\\src\\mirrors.ustc.edu.cn-b63e9dae659fc205\\vcpkg-0.2.10\\src\\lib.rs","byte_start":1885,"byte_end":1888,"line_start":39,"line_end":39,"column_start":1,"column_end":4}},{"value":"! A number of environment variables are available to globally configure which","span":{"file_name":"C:\\Users\\12935\\.cargo\\registry\\src\\mirrors.ustc.edu.cn-b63e9dae659fc205\\vcpkg-0.2.10\\src\\lib.rs","byte_start":1889,"byte_end":1968,"line_start":40,"line_end":40,"column_start":1,"column_end":80}},{"value":"! libraries are selected.","span":{"file_name":"C:\\Users\\12935\\.cargo\\registry\\src\\mirrors.ustc.edu.cn-b63e9dae659fc205\\vcpkg-0.2.10\\src\\lib.rs","byte_start":1969,"byte_end":1996,"line_start":41,"line_end":41,"column_start":1,"column_end":28}},{"value":"!","span":{"file_name":"C:\\Users\\12935\\.cargo\\registry\\src\\mirrors.ustc.edu.cn-b63e9dae659fc205\\vcpkg-0.2.10\\src\\lib.rs","byte_start":1997,"byte_end":2000,"line_start":42,"line_end":42,"column_start":1,"column_end":4}},{"value":"! * `VCPKG_ROOT` - Set the directory to look in for a vcpkg installation. If","span":{"file_name":"C:\\Users\\12935\\.cargo\\registry\\src\\mirrors.ustc.edu.cn-b63e9dae659fc205\\vcpkg-0.2.10\\src\\lib.rs","byte_start":2001,"byte_end":2079,"line_start":43,"line_end":43,"column_start":1,"column_end":79}},{"value":"! it is not set, vcpkg will use the user-wide installation if one has been","span":{"file_name":"C:\\Users\\12935\\.cargo\\registry\\src\\mirrors.ustc.edu.cn-b63e9dae659fc205\\vcpkg-0.2.10\\src\\lib.rs","byte_start":2080,"byte_end":2156,"line_start":44,"line_end":44,"column_start":1,"column_end":77}},{"value":"! set up with `vcpkg integrate install`, and check the crate source and target","span":{"file_name":"C:\\Users\\12935\\.cargo\\registry\\src\\mirrors.ustc.edu.cn-b63e9dae659fc205\\vcpkg-0.2.10\\src\\lib.rs","byte_start":2157,"byte_end":2237,"line_start":45,"line_end":45,"column_start":1,"column_end":81}},{"value":"! to see if a vcpkg tree has been created by [cargo-vcpkg](https://crates.io/crates/cargo-vcpkg).","span":{"file_name":"C:\\Users\\12935\\.cargo\\registry\\src\\mirrors.ustc.edu.cn-b63e9dae659fc205\\vcpkg-0.2.10\\src\\lib.rs","byte_start":2238,"byte_end":2337,"line_start":46,"line_end":46,"column_start":1,"column_end":100}},{"value":"!","span":{"file_name":"C:\\Users\\12935\\.cargo\\registry\\src\\mirrors.ustc.edu.cn-b63e9dae659fc205\\vcpkg-0.2.10\\src\\lib.rs","byte_start":2338,"byte_end":2341,"line_start":47,"line_end":47,"column_start":1,"column_end":4}},{"value":"! * `VCPKGRS_NO_FOO` - if set, vcpkg-rs will not attempt to find the","span":{"file_name":"C:\\Users\\12935\\.cargo\\registry\\src\\mirrors.ustc.edu.cn-b63e9dae659fc205\\vcpkg-0.2.10\\src\\lib.rs","byte_start":2342,"byte_end":2412,"line_start":48,"line_end":48,"column_start":1,"column_end":71}},{"value":"! library named `foo`.","span":{"file_name":"C:\\Users\\12935\\.cargo\\registry\\src\\mirrors.ustc.edu.cn-b63e9dae659fc205\\vcpkg-0.2.10\\src\\lib.rs","byte_start":2413,"byte_end":2437,"line_start":49,"line_end":49,"column_start":1,"column_end":25}},{"value":"!","span":{"file_name":"C:\\Users\\12935\\.cargo\\registry\\src\\mirrors.ustc.edu.cn-b63e9dae659fc205\\vcpkg-0.2.10\\src\\lib.rs","byte_start":2438,"byte_end":2441,"line_start":50,"line_end":50,"column_start":1,"column_end":4}},{"value":"! * `VCPKGRS_DISABLE` - if set, vcpkg-rs will not attempt to find any libraries.","span":{"file_name":"C:\\Users\\12935\\.cargo\\registry\\src\\mirrors.ustc.edu.cn-b63e9dae659fc205\\vcpkg-0.2.10\\src\\lib.rs","byte_start":2442,"byte_end":2524,"line_start":51,"line_end":51,"column_start":1,"column_end":83}},{"value":"!","span":{"file_name":"C:\\Users\\12935\\.cargo\\registry\\src\\mirrors.ustc.edu.cn-b63e9dae659fc205\\vcpkg-0.2.10\\src\\lib.rs","byte_start":2525,"byte_end":2528,"line_start":52,"line_end":52,"column_start":1,"column_end":4}},{"value":"! * `VCPKGRS_DYNAMIC` - if set, vcpkg-rs will link to DLL builds of ports.","span":{"file_name":"C:\\Users\\12935\\.cargo\\registry\\src\\mirrors.ustc.edu.cn-b63e9dae659fc205\\vcpkg-0.2.10\\src\\lib.rs","byte_start":2529,"byte_end":2605,"line_start":53,"line_end":53,"column_start":1,"column_end":77}},{"value":"!","span":{"file_name":"C:\\Users\\12935\\.cargo\\registry\\src\\mirrors.ustc.edu.cn-b63e9dae659fc205\\vcpkg-0.2.10\\src\\lib.rs","byte_start":2606,"byte_end":2609,"line_start":54,"line_end":54,"column_start":1,"column_end":4}},{"value":"! There is a companion crate `vcpkg_cli` that allows testing of environment","span":{"file_name":"C:\\Users\\12935\\.cargo\\registry\\src\\mirrors.ustc.edu.cn-b63e9dae659fc205\\vcpkg-0.2.10\\src\\lib.rs","byte_start":2610,"byte_end":2687,"line_start":55,"line_end":55,"column_start":1,"column_end":78}},{"value":"! and flag combinations.","span":{"file_name":"C:\\Users\\12935\\.cargo\\registry\\src\\mirrors.ustc.edu.cn-b63e9dae659fc205\\vcpkg-0.2.10\\src\\lib.rs","byte_start":2688,"byte_end":2714,"line_start":56,"line_end":56,"column_start":1,"column_end":27}},{"value":"!","span":{"file_name":"C:\\Users\\12935\\.cargo\\registry\\src\\mirrors.ustc.edu.cn-b63e9dae659fc205\\vcpkg-0.2.10\\src\\lib.rs","byte_start":2715,"byte_end":2718,"line_start":57,"line_end":57,"column_start":1,"column_end":4}},{"value":"! ```Batchfile","span":{"file_name":"C:\\Users\\12935\\.cargo\\registry\\src\\mirrors.ustc.edu.cn-b63e9dae659fc205\\vcpkg-0.2.10\\src\\lib.rs","byte_start":2719,"byte_end":2735,"line_start":58,"line_end":58,"column_start":1,"column_end":17}},{"value":"! C:\\src> vcpkg_cli probe -l static mysqlclient","span":{"file_name":"C:\\Users\\12935\\.cargo\\registry\\src\\mirrors.ustc.edu.cn-b63e9dae659fc205\\vcpkg-0.2.10\\src\\lib.rs","byte_start":2736,"byte_end":2785,"line_start":59,"line_end":59,"column_start":1,"column_end":50}},{"value":"! Found library mysqlclient","span":{"file_name":"C:\\Users\\12935\\.cargo\\registry\\src\\mirrors.ustc.edu.cn-b63e9dae659fc205\\vcpkg-0.2.10\\src\\lib.rs","byte_start":2786,"byte_end":2815,"line_start":60,"line_end":60,"column_start":1,"column_end":30}},{"value":"! Include paths:","span":{"file_name":"C:\\Users\\12935\\.cargo\\registry\\src\\mirrors.ustc.edu.cn-b63e9dae659fc205\\vcpkg-0.2.10\\src\\lib.rs","byte_start":2816,"byte_end":2834,"line_start":61,"line_end":61,"column_start":1,"column_end":19}},{"value":"!         C:\\src\\[..]\\vcpkg\\installed\\x64-windows-static\\include","span":{"file_name":"C:\\Users\\12935\\.cargo\\registry\\src\\mirrors.ustc.edu.cn-b63e9dae659fc205\\vcpkg-0.2.10\\src\\lib.rs","byte_start":2835,"byte_end":2901,"line_start":62,"line_end":62,"column_start":1,"column_end":67}},{"value":"! Library paths:","span":{"file_name":"C:\\Users\\12935\\.cargo\\registry\\src\\mirrors.ustc.edu.cn-b63e9dae659fc205\\vcpkg-0.2.10\\src\\lib.rs","byte_start":2902,"byte_end":2920,"line_start":63,"line_end":63,"column_start":1,"column_end":19}},{"value":"!         C:\\src\\[..]\\vcpkg\\installed\\x64-windows-static\\lib","span":{"file_name":"C:\\Users\\12935\\.cargo\\registry\\src\\mirrors.ustc.edu.cn-b63e9dae659fc205\\vcpkg-0.2.10\\src\\lib.rs","byte_start":2921,"byte_end":2983,"line_start":64,"line_end":64,"column_start":1,"column_end":63}},{"value":"! Cargo metadata:","span":{"file_name":"C:\\Users\\12935\\.cargo\\registry\\src\\mirrors.ustc.edu.cn-b63e9dae659fc205\\vcpkg-0.2.10\\src\\lib.rs","byte_start":2984,"byte_end":3003,"line_start":65,"line_end":65,"column_start":1,"column_end":20}},{"value":"!         cargo:rustc-link-search=native=C:\\src\\[..]\\vcpkg\\installed\\x64-windows-static\\lib","span":{"file_name":"C:\\Users\\12935\\.cargo\\registry\\src\\mirrors.ustc.edu.cn-b63e9dae659fc205\\vcpkg-0.2.10\\src\\lib.rs","byte_start":3004,"byte_end":3097,"line_start":66,"line_end":66,"column_start":1,"column_end":94}},{"value":"!         cargo:rustc-link-lib=static=mysqlclient","span":{"file_name":"C:\\Users\\12935\\.cargo\\registry\\src\\mirrors.ustc.edu.cn-b63e9dae659fc205\\vcpkg-0.2.10\\src\\lib.rs","byte_start":3098,"byte_end":3149,"line_start":67,"line_end":67,"column_start":1,"column_end":52}},{"value":"! ```","span":{"file_name":"C:\\Users\\12935\\.cargo\\registry\\src\\mirrors.ustc.edu.cn-b63e9dae659fc205\\vcpkg-0.2.10\\src\\lib.rs","byte_start":3150,"byte_end":3157,"line_start":68,"line_end":68,"column_start":1,"column_end":8}},{"value":"allow(deprecated)","span":{"file_name":"C:\\Users\\12935\\.cargo\\registry\\src\\mirrors.ustc.edu.cn-b63e9dae659fc205\\vcpkg-0.2.10\\src\\lib.rs","byte_start":3385,"byte_end":3406,"line_start":73,"line_end":73,"column_start":1,"column_end":22}},{"value":"allow(warnings)","span":{"file_name":"C:\\Users\\12935\\.cargo\\registry\\src\\mirrors.ustc.edu.cn-b63e9dae659fc205\\vcpkg-0.2.10\\src\\lib.rs","byte_start":3407,"byte_end":3426,"line_start":74,"line_end":74,"column_start":1,"column_end":20}}]},{"kind":"Struct","id":{"krate":0,"index":73},"span":{"file_name":"C:\\Users\\12935\\.cargo\\registry\\src\\mirrors.ustc.edu.cn-b63e9dae659fc205\\vcpkg-0.2.10\\src\\lib.rs","byte_start":3854,"byte_end":3860,"line_start":94,"line_end":94,"column_start":12,"column_end":18},"name":"Config","qualname":"::Config","value":"Config {  }","parent":null,"children":[{"krate":0,"index":74},{"krate":0,"index":75},{"krate":0,"index":76},{"krate":0,"index":77},{"krate":0,"index":78},{"krate":0,"index":79}],"decl_id":null,"docs":" Configuration options for finding packages, setting up the tree and emitting metadata to cargo\n","sig":null,"attributes":[{"value":"/ Configuration options for finding packages, setting up the tree and emitting metadata to cargo","span":{"file_name":"C:\\Users\\12935\\.cargo\\registry\\src\\mirrors.ustc.edu.cn-b63e9dae659fc205\\vcpkg-0.2.10\\src\\lib.rs","byte_start":3725,"byte_end":3823,"line_start":92,"line_end":92,"column_start":1,"column_end":99}}]},{"kind":"Struct","id":{"krate":0,"index":82},"span":{"file_name":"C:\\Users\\12935\\.cargo\\registry\\src\\mirrors.ustc.edu.cn-b63e9dae659fc205\\vcpkg-0.2.10\\src\\lib.rs","byte_start":4483,"byte_end":4490,"line_start":116,"line_end":116,"column_start":12,"column_end":19},"name":"Library","qualname":"::Library","value":"Library { link_paths, dll_paths, include_paths, cargo_metadata, is_static, found_dlls, found_libs, found_names, ports }","parent":null,"children":[{"krate":0,"index":83},{"krate":0,"index":84},{"krate":0,"index":85},{"krate":0,"index":86},{"krate":0,"index":87},{"krate":0,"index":88},{"krate":0,"index":89},{"krate":0,"index":90},{"krate":0,"index":91}],"decl_id":null,"docs":" Details of a package that was found\n","sig":null,"attributes":[{"value":"/ Details of a package that was found","span":{"file_name":"C:\\Users\\12935\\.cargo\\registry\\src\\mirrors.ustc.edu.cn-b63e9dae659fc205\\vcpkg-0.2.10\\src\\lib.rs","byte_start":4415,"byte_end":4454,"line_start":114,"line_end":114,"column_start":1,"column_end":40}}]},{"kind":"Field","id":{"krate":0,"index":83},"span":{"file_name":"C:\\Users\\12935\\.cargo\\registry\\src\\mirrors.ustc.edu.cn-b63e9dae659fc205\\vcpkg-0.2.10\\src\\lib.rs","byte_start":4571,"byte_end":4581,"line_start":118,"line_end":118,"column_start":9,"column_end":19},"name":"link_paths","qualname":"::Library::link_paths","value":"std::vec::Vec<std::path::PathBuf>","parent":{"krate":0,"index":82},"children":[],"decl_id":null,"docs":" Paths for the linker to search for static or import libraries\n","sig":null,"attributes":[{"value":"/ Paths for the linker to search for static or import libraries","span":{"file_name":"C:\\Users\\12935\\.cargo\\registry\\src\\mirrors.ustc.edu.cn-b63e9dae659fc205\\vcpkg-0.2.10\\src\\lib.rs","byte_start":4497,"byte_end":4562,"line_start":117,"line_end":117,"column_start":5,"column_end":70}}]},{"kind":"Field","id":{"krate":0,"index":84},"span":{"file_name":"C:\\Users\\12935\\.cargo\\registry\\src\\mirrors.ustc.edu.cn-b63e9dae659fc205\\vcpkg-0.2.10\\src\\lib.rs","byte_start":4653,"byte_end":4662,"line_start":121,"line_end":121,"column_start":9,"column_end":18},"name":"dll_paths","qualname":"::Library::dll_paths","value":"std::vec::Vec<std::path::PathBuf>","parent":{"krate":0,"index":82},"children":[],"decl_id":null,"docs":" Paths to search at runtme to find DLLs\n","sig":null,"attributes":[{"value":"/ Paths to search at runtme to find DLLs","span":{"file_name":"C:\\Users\\12935\\.cargo\\registry\\src\\mirrors.ustc.edu.cn-b63e9dae659fc205\\vcpkg-0.2.10\\src\\lib.rs","byte_start":4602,"byte_end":4644,"line_start":120,"line_end":120,"column_start":5,"column_end":47}}]},{"kind":"Field","id":{"krate":0,"index":85},"span":{"file_name":"C:\\Users\\12935\\.cargo\\registry\\src\\mirrors.ustc.edu.cn-b63e9dae659fc205\\vcpkg-0.2.10\\src\\lib.rs","byte_start":4718,"byte_end":4731,"line_start":124,"line_end":124,"column_start":9,"column_end":22},"name":"include_paths","qualname":"::Library::include_paths","value":"std::vec::Vec<std::path::PathBuf>","parent":{"krate":0,"index":82},"children":[],"decl_id":null,"docs":" Paths to include files\n","sig":null,"attributes":[{"value":"/ Paths to include files","span":{"file_name":"C:\\Users\\12935\\.cargo\\registry\\src\\mirrors.ustc.edu.cn-b63e9dae659fc205\\vcpkg-0.2.10\\src\\lib.rs","byte_start":4683,"byte_end":4709,"line_start":123,"line_end":123,"column_start":5,"column_end":31}}]},{"kind":"Field","id":{"krate":0,"index":86},"span":{"file_name":"C:\\Users\\12935\\.cargo\\registry\\src\\mirrors.ustc.edu.cn-b63e9dae659fc205\\vcpkg-0.2.10\\src\\lib.rs","byte_start":4786,"byte_end":4800,"line_start":127,"line_end":127,"column_start":9,"column_end":23},"name":"cargo_metadata","qualname":"::Library::cargo_metadata","value":"std::vec::Vec<std::string::String>","parent":{"krate":0,"index":82},"children":[],"decl_id":null,"docs":" cargo: metadata lines\n","sig":null,"attributes":[{"value":"/ cargo: metadata lines","span":{"file_name":"C:\\Users\\12935\\.cargo\\registry\\src\\mirrors.ustc.edu.cn-b63e9dae659fc205\\vcpkg-0.2.10\\src\\lib.rs","byte_start":4752,"byte_end":4777,"line_start":126,"line_end":126,"column_start":5,"column_end":30}}]},{"kind":"Field","id":{"krate":0,"index":87},"span":{"file_name":"C:\\Users\\12935\\.cargo\\registry\\src\\mirrors.ustc.edu.cn-b63e9dae659fc205\\vcpkg-0.2.10\\src\\lib.rs","byte_start":4859,"byte_end":4868,"line_start":130,"line_end":130,"column_start":9,"column_end":18},"name":"is_static","qualname":"::Library::is_static","value":"bool","parent":{"krate":0,"index":82},"children":[],"decl_id":null,"docs":" libraries found are static\n","sig":null,"attributes":[{"value":"/ libraries found are static","span":{"file_name":"C:\\Users\\12935\\.cargo\\registry\\src\\mirrors.ustc.edu.cn-b63e9dae659fc205\\vcpkg-0.2.10\\src\\lib.rs","byte_start":4820,"byte_end":4850,"line_start":129,"line_end":129,"column_start":5,"column_end":35}}]},{"kind":"Field","id":{"krate":0,"index":88},"span":{"file_name":"C:\\Users\\12935\\.cargo\\registry\\src\\mirrors.ustc.edu.cn-b63e9dae659fc205\\vcpkg-0.2.10\\src\\lib.rs","byte_start":4904,"byte_end":4914,"line_start":133,"line_end":133,"column_start":9,"column_end":19},"name":"found_dlls","qualname":"::Library::found_dlls","value":"std::vec::Vec<std::path::PathBuf>","parent":{"krate":0,"index":82},"children":[],"decl_id":null,"docs":" DLLs found\n","sig":null,"attributes":[{"value":"/ DLLs found","span":{"file_name":"C:\\Users\\12935\\.cargo\\registry\\src\\mirrors.ustc.edu.cn-b63e9dae659fc205\\vcpkg-0.2.10\\src\\lib.rs","byte_start":4881,"byte_end":4895,"line_start":132,"line_end":132,"column_start":5,"column_end":19}}]},{"kind":"Field","id":{"krate":0,"index":89},"span":{"file_name":"C:\\Users\\12935\\.cargo\\registry\\src\\mirrors.ustc.edu.cn-b63e9dae659fc205\\vcpkg-0.2.10\\src\\lib.rs","byte_start":4980,"byte_end":4990,"line_start":136,"line_end":136,"column_start":9,"column_end":19},"name":"found_libs","qualname":"::Library::found_libs","value":"std::vec::Vec<std::path::PathBuf>","parent":{"krate":0,"index":82},"children":[],"decl_id":null,"docs":" static libs or import libs found\n","sig":null,"attributes":[{"value":"/ static libs or import libs found","span":{"file_name":"C:\\Users\\12935\\.cargo\\registry\\src\\mirrors.ustc.edu.cn-b63e9dae659fc205\\vcpkg-0.2.10\\src\\lib.rs","byte_start":4935,"byte_end":4971,"line_start":135,"line_end":135,"column_start":5,"column_end":41}}]},{"kind":"Field","id":{"krate":0,"index":90},"span":{"file_name":"C:\\Users\\12935\\.cargo\\registry\\src\\mirrors.ustc.edu.cn-b63e9dae659fc205\\vcpkg-0.2.10\\src\\lib.rs","byte_start":5092,"byte_end":5103,"line_start":139,"line_end":139,"column_start":9,"column_end":20},"name":"found_names","qualname":"::Library::found_names","value":"std::vec::Vec<std::string::String>","parent":{"krate":0,"index":82},"children":[],"decl_id":null,"docs":" link name of libraries found, this is useful to emit linker commands\n","sig":null,"attributes":[{"value":"/ link name of libraries found, this is useful to emit linker commands","span":{"file_name":"C:\\Users\\12935\\.cargo\\registry\\src\\mirrors.ustc.edu.cn-b63e9dae659fc205\\vcpkg-0.2.10\\src\\lib.rs","byte_start":5011,"byte_end":5083,"line_start":138,"line_end":138,"column_start":5,"column_end":77}}]},{"kind":"Field","id":{"krate":0,"index":91},"span":{"file_name":"C:\\Users\\12935\\.cargo\\registry\\src\\mirrors.ustc.edu.cn-b63e9dae659fc205\\vcpkg-0.2.10\\src\\lib.rs","byte_start":5205,"byte_end":5210,"line_start":142,"line_end":142,"column_start":9,"column_end":14},"name":"ports","qualname":"::Library::ports","value":"std::vec::Vec<std::string::String>","parent":{"krate":0,"index":82},"children":[],"decl_id":null,"docs":" ports that are providing the libraries to link to, in port link order\n","sig":null,"attributes":[{"value":"/ ports that are providing the libraries to link to, in port link order","span":{"file_name":"C:\\Users\\12935\\.cargo\\registry\\src\\mirrors.ustc.edu.cn-b63e9dae659fc205\\vcpkg-0.2.10\\src\\lib.rs","byte_start":5123,"byte_end":5196,"line_start":141,"line_end":141,"column_start":5,"column_end":78}}]},{"kind":"TupleVariant","id":{"krate":0,"index":95},"span":{"file_name":"C:\\Users\\12935\\.cargo\\registry\\src\\mirrors.ustc.edu.cn-b63e9dae659fc205\\vcpkg-0.2.10\\src\\lib.rs","byte_start":5544,"byte_end":5557,"line_start":157,"line_end":157,"column_start":5,"column_end":18},"name":"DisabledByEnv","qualname":"::Error::DisabledByEnv","value":"Error::DisabledByEnv(String)","parent":{"krate":0,"index":94},"children":[],"decl_id":null,"docs":" Aborted because of a `VCPKGRS_NO_*` environment variable.","sig":null,"attributes":[{"value":"/ Aborted because of a `VCPKGRS_NO_*` environment variable.","span":{"file_name":"C:\\Users\\12935\\.cargo\\registry\\src\\mirrors.ustc.edu.cn-b63e9dae659fc205\\vcpkg-0.2.10\\src\\lib.rs","byte_start":5403,"byte_end":5464,"line_start":154,"line_end":154,"column_start":5,"column_end":66}},{"value":"/","span":{"file_name":"C:\\Users\\12935\\.cargo\\registry\\src\\mirrors.ustc.edu.cn-b63e9dae659fc205\\vcpkg-0.2.10\\src\\lib.rs","byte_start":5469,"byte_end":5472,"line_start":155,"line_end":155,"column_start":5,"column_end":8}},{"value":"/ Contains the name of the responsible environment variable.","span":{"file_name":"C:\\Users\\12935\\.cargo\\registry\\src\\mirrors.ustc.edu.cn-b63e9dae659fc205\\vcpkg-0.2.10\\src\\lib.rs","byte_start":5477,"byte_end":5539,"line_start":156,"line_end":156,"column_start":5,"column_end":67}}]},{"kind":"TupleVariant","id":{"krate":0,"index":98},"span":{"file_name":"C:\\Users\\12935\\.cargo\\registry\\src\\mirrors.ustc.edu.cn-b63e9dae659fc205\\vcpkg-0.2.10\\src\\lib.rs","byte_start":5641,"byte_end":5659,"line_start":160,"line_end":160,"column_start":5,"column_end":23},"name":"RequiredEnvMissing","qualname":"::Error::RequiredEnvMissing","value":"Error::RequiredEnvMissing(String)","parent":{"krate":0,"index":94},"children":[],"decl_id":null,"docs":" Aborted because a required environment variable was not set.\n","sig":null,"attributes":[{"value":"/ Aborted because a required environment variable was not set.","span":{"file_name":"C:\\Users\\12935\\.cargo\\registry\\src\\mirrors.ustc.edu.cn-b63e9dae659fc205\\vcpkg-0.2.10\\src\\lib.rs","byte_start":5572,"byte_end":5636,"line_start":159,"line_end":159,"column_start":5,"column_end":69}}]},{"kind":"TupleVariant","id":{"krate":0,"index":101},"span":{"file_name":"C:\\Users\\12935\\.cargo\\registry\\src\\mirrors.ustc.edu.cn-b63e9dae659fc205\\vcpkg-0.2.10\\src\\lib.rs","byte_start":5721,"byte_end":5728,"line_start":163,"line_end":163,"column_start":5,"column_end":12},"name":"NotMSVC","qualname":"::Error::NotMSVC","value":"Error::NotMSVC","parent":{"krate":0,"index":94},"children":[],"decl_id":null,"docs":" On Windows, only MSVC ABI is supported\n","sig":null,"attributes":[{"value":"/ On Windows, only MSVC ABI is supported","span":{"file_name":"C:\\Users\\12935\\.cargo\\registry\\src\\mirrors.ustc.edu.cn-b63e9dae659fc205\\vcpkg-0.2.10\\src\\lib.rs","byte_start":5674,"byte_end":5716,"line_start":162,"line_end":162,"column_start":5,"column_end":47}}]},{"kind":"TupleVariant","id":{"krate":0,"index":103},"span":{"file_name":"C:\\Users\\12935\\.cargo\\registry\\src\\mirrors.ustc.edu.cn-b63e9dae659fc205\\vcpkg-0.2.10\\src\\lib.rs","byte_start":5767,"byte_end":5780,"line_start":166,"line_end":166,"column_start":5,"column_end":18},"name":"VcpkgNotFound","qualname":"::Error::VcpkgNotFound","value":"Error::VcpkgNotFound(String)","parent":{"krate":0,"index":94},"children":[],"decl_id":null,"docs":" Can't find a vcpkg tree\n","sig":null,"attributes":[{"value":"/ Can't find a vcpkg tree","span":{"file_name":"C:\\Users\\12935\\.cargo\\registry\\src\\mirrors.ustc.edu.cn-b63e9dae659fc205\\vcpkg-0.2.10\\src\\lib.rs","byte_start":5735,"byte_end":5762,"line_start":165,"line_end":165,"column_start":5,"column_end":32}}]},{"kind":"TupleVariant","id":{"krate":0,"index":106},"span":{"file_name":"C:\\Users\\12935\\.cargo\\registry\\src\\mirrors.ustc.edu.cn-b63e9dae659fc205\\vcpkg-0.2.10\\src\\lib.rs","byte_start":5835,"byte_end":5846,"line_start":169,"line_end":169,"column_start":5,"column_end":16},"name":"LibNotFound","qualname":"::Error::LibNotFound","value":"Error::LibNotFound(String)","parent":{"krate":0,"index":94},"children":[],"decl_id":null,"docs":" Library not found in vcpkg tree\n","sig":null,"attributes":[{"value":"/ Library not found in vcpkg tree","span":{"file_name":"C:\\Users\\12935\\.cargo\\registry\\src\\mirrors.ustc.edu.cn-b63e9dae659fc205\\vcpkg-0.2.10\\src\\lib.rs","byte_start":5795,"byte_end":5830,"line_start":168,"line_end":168,"column_start":5,"column_end":40}}]},{"kind":"TupleVariant","id":{"krate":0,"index":109},"span":{"file_name":"C:\\Users\\12935\\.cargo\\registry\\src\\mirrors.ustc.edu.cn-b63e9dae659fc205\\vcpkg-0.2.10\\src\\lib.rs","byte_start":5909,"byte_end":5926,"line_start":172,"line_end":172,"column_start":5,"column_end":22},"name":"VcpkgInstallation","qualname":"::Error::VcpkgInstallation","value":"Error::VcpkgInstallation(String)","parent":{"krate":0,"index":94},"children":[],"decl_id":null,"docs":" Could not understand vcpkg installation\n","sig":null,"attributes":[{"value":"/ Could not understand vcpkg installation","span":{"file_name":"C:\\Users\\12935\\.cargo\\registry\\src\\mirrors.ustc.edu.cn-b63e9dae659fc205\\vcpkg-0.2.10\\src\\lib.rs","byte_start":5861,"byte_end":5904,"line_start":171,"line_end":171,"column_start":5,"column_end":48}}]},{"kind":"TupleVariant","id":{"krate":0,"index":112},"span":{"file_name":"C:\\Users\\12935\\.cargo\\registry\\src\\mirrors.ustc.edu.cn-b63e9dae659fc205\\vcpkg-0.2.10\\src\\lib.rs","byte_start":5960,"byte_end":5975,"line_start":175,"line_end":175,"column_start":5,"column_end":20},"name":"__Nonexhaustive","qualname":"::Error::__Nonexhaustive","value":"Error::__Nonexhaustive","parent":{"krate":0,"index":94},"children":[],"decl_id":null,"docs":"","sig":null,"attributes":[]},{"kind":"Enum","id":{"krate":0,"index":94},"span":{"file_name":"C:\\Users\\12935\\.cargo\\registry\\src\\mirrors.ustc.edu.cn-b63e9dae659fc205\\vcpkg-0.2.10\\src\\lib.rs","byte_start":5391,"byte_end":5396,"line_start":153,"line_end":153,"column_start":10,"column_end":15},"name":"Error","qualname":"::Error","value":"Error::{DisabledByEnv, RequiredEnvMissing, NotMSVC, VcpkgNotFound, LibNotFound, VcpkgInstallation, __Nonexhaustive}","parent":null,"children":[{"krate":0,"index":95},{"krate":0,"index":98},{"krate":0,"index":101},{"krate":0,"index":103},{"krate":0,"index":106},{"krate":0,"index":109},{"krate":0,"index":112}],"decl_id":null,"docs":"","sig":null,"attributes":[]},{"kind":"Function","id":{"krate":0,"index":28},"span":{"file_name":"C:\\Users\\12935\\.cargo\\registry\\src\\mirrors.ustc.edu.cn-b63e9dae659fc205\\vcpkg-0.2.10\\src\\lib.rs","byte_start":7855,"byte_end":7868,"line_start":224,"line_end":224,"column_start":8,"column_end":21},"name":"probe_package","qualname":"::probe_package","value":"fn (name: &str) -> Result<Library, Error>","parent":null,"children":[],"decl_id":null,"docs":" Deprecated in favor of the find_package function\n","sig":null,"attributes":[{"value":"/ Deprecated in favor of the find_package function","span":{"file_name":"C:\\Users\\12935\\.cargo\\registry\\src\\mirrors.ustc.edu.cn-b63e9dae659fc205\\vcpkg-0.2.10\\src\\lib.rs","byte_start":7780,"byte_end":7832,"line_start":222,"line_end":222,"column_start":1,"column_end":53}}]},{"kind":"Function","id":{"krate":0,"index":29},"span":{"file_name":"C:\\Users\\12935\\.cargo\\registry\\src\\mirrors.ustc.edu.cn-b63e9dae659fc205\\vcpkg-0.2.10\\src\\lib.rs","byte_start":8283,"byte_end":8295,"line_start":235,"line_end":235,"column_start":8,"column_end":20},"name":"find_package","qualname":"::find_package","value":"fn (package: &str) -> Result<Library, Error>","parent":null,"children":[],"decl_id":null,"docs":" Find the package `package` in a Vcpkg tree.","sig":null,"attributes":[{"value":"/ Find the package `package` in a Vcpkg tree.","span":{"file_name":"C:\\Users\\12935\\.cargo\\registry\\src\\mirrors.ustc.edu.cn-b63e9dae659fc205\\vcpkg-0.2.10\\src\\lib.rs","byte_start":7942,"byte_end":7989,"line_start":228,"line_end":228,"column_start":1,"column_end":48}},{"value":"/","span":{"file_name":"C:\\Users\\12935\\.cargo\\registry\\src\\mirrors.ustc.edu.cn-b63e9dae659fc205\\vcpkg-0.2.10\\src\\lib.rs","byte_start":7990,"byte_end":7993,"line_start":229,"line_end":229,"column_start":1,"column_end":4}},{"value":"/ Emits cargo metadata to link to libraries provided by the Vcpkg package/port","span":{"file_name":"C:\\Users\\12935\\.cargo\\registry\\src\\mirrors.ustc.edu.cn-b63e9dae659fc205\\vcpkg-0.2.10\\src\\lib.rs","byte_start":7994,"byte_end":8074,"line_start":230,"line_end":230,"column_start":1,"column_end":81}},{"value":"/ named, and any (non-system) libraries that they depend on.","span":{"file_name":"C:\\Users\\12935\\.cargo\\registry\\src\\mirrors.ustc.edu.cn-b63e9dae659fc205\\vcpkg-0.2.10\\src\\lib.rs","byte_start":8075,"byte_end":8137,"line_start":231,"line_end":231,"column_start":1,"column_end":63}},{"value":"/","span":{"file_name":"C:\\Users\\12935\\.cargo\\registry\\src\\mirrors.ustc.edu.cn-b63e9dae659fc205\\vcpkg-0.2.10\\src\\lib.rs","byte_start":8138,"byte_end":8141,"line_start":232,"line_end":232,"column_start":1,"column_end":4}},{"value":"/ This will select the architecture and linkage based on environment","span":{"file_name":"C:\\Users\\12935\\.cargo\\registry\\src\\mirrors.ustc.edu.cn-b63e9dae659fc205\\vcpkg-0.2.10\\src\\lib.rs","byte_start":8142,"byte_end":8212,"line_start":233,"line_end":233,"column_start":1,"column_end":71}},{"value":"/ variables and build flags as described in the module docs.","span":{"file_name":"C:\\Users\\12935\\.cargo\\registry\\src\\mirrors.ustc.edu.cn-b63e9dae659fc205\\vcpkg-0.2.10\\src\\lib.rs","byte_start":8213,"byte_end":8275,"line_start":234,"line_end":234,"column_start":1,"column_end":63}}]},{"kind":"Function","id":{"krate":0,"index":30},"span":{"file_name":"C:\\Users\\12935\\.cargo\\registry\\src\\mirrors.ustc.edu.cn-b63e9dae659fc205\\vcpkg-0.2.10\\src\\lib.rs","byte_start":8428,"byte_end":8443,"line_start":241,"line_end":241,"column_start":8,"column_end":23},"name":"find_vcpkg_root","qualname":"::find_vcpkg_root","value":"fn (cfg: &Config) -> Result<PathBuf, Error>","parent":null,"children":[],"decl_id":null,"docs":" Find the vcpkg root\n","sig":null,"attributes":[{"value":"/ Find the vcpkg root","span":{"file_name":"C:\\Users\\12935\\.cargo\\registry\\src\\mirrors.ustc.edu.cn-b63e9dae659fc205\\vcpkg-0.2.10\\src\\lib.rs","byte_start":8382,"byte_end":8405,"line_start":239,"line_end":239,"column_start":1,"column_end":24}}]},{"kind":"Method","id":{"krate":0,"index":52},"span":{"file_name":"C:\\Users\\12935\\.cargo\\registry\\src\\mirrors.ustc.edu.cn-b63e9dae659fc205\\vcpkg-0.2.10\\src\\lib.rs","byte_start":21441,"byte_end":21444,"line_start":618,"line_end":618,"column_start":12,"column_end":15},"name":"new","qualname":"<Config>::new","value":"fn () -> Config","parent":null,"children":[],"decl_id":null,"docs":"","sig":null,"attributes":[]},{"kind":"Method","id":{"krate":0,"index":53},"span":{"file_name":"C:\\Users\\12935\\.cargo\\registry\\src\\mirrors.ustc.edu.cn-b63e9dae659fc205\\vcpkg-0.2.10\\src\\lib.rs","byte_start":22014,"byte_end":22026,"line_start":634,"line_end":634,"column_start":12,"column_end":24},"name":"find_package","qualname":"<Config>::find_package","value":"fn (&mut self, port_name: &str) -> Result<Library, Error>","parent":null,"children":[],"decl_id":null,"docs":" Find the package `port_name` in a Vcpkg tree.","sig":null,"attributes":[{"value":"/ Find the package `port_name` in a Vcpkg tree.","span":{"file_name":"C:\\Users\\12935\\.cargo\\registry\\src\\mirrors.ustc.edu.cn-b63e9dae659fc205\\vcpkg-0.2.10\\src\\lib.rs","byte_start":21593,"byte_end":21642,"line_start":626,"line_end":626,"column_start":5,"column_end":54}},{"value":"/","span":{"file_name":"C:\\Users\\12935\\.cargo\\registry\\src\\mirrors.ustc.edu.cn-b63e9dae659fc205\\vcpkg-0.2.10\\src\\lib.rs","byte_start":21647,"byte_end":21650,"line_start":627,"line_end":627,"column_start":5,"column_end":8}},{"value":"/ Emits cargo metadata to link to libraries provided by the Vcpkg package/port","span":{"file_name":"C:\\Users\\12935\\.cargo\\registry\\src\\mirrors.ustc.edu.cn-b63e9dae659fc205\\vcpkg-0.2.10\\src\\lib.rs","byte_start":21655,"byte_end":21735,"line_start":628,"line_end":628,"column_start":5,"column_end":85}},{"value":"/ named, and any (non-system) libraries that they depend on.","span":{"file_name":"C:\\Users\\12935\\.cargo\\registry\\src\\mirrors.ustc.edu.cn-b63e9dae659fc205\\vcpkg-0.2.10\\src\\lib.rs","byte_start":21740,"byte_end":21802,"line_start":629,"line_end":629,"column_start":5,"column_end":67}},{"value":"/","span":{"file_name":"C:\\Users\\12935\\.cargo\\registry\\src\\mirrors.ustc.edu.cn-b63e9dae659fc205\\vcpkg-0.2.10\\src\\lib.rs","byte_start":21807,"byte_end":21810,"line_start":630,"line_end":630,"column_start":5,"column_end":8}},{"value":"/ This will select the architecture and linkage based on environment","span":{"file_name":"C:\\Users\\12935\\.cargo\\registry\\src\\mirrors.ustc.edu.cn-b63e9dae659fc205\\vcpkg-0.2.10\\src\\lib.rs","byte_start":21815,"byte_end":21885,"line_start":631,"line_end":631,"column_start":5,"column_end":75}},{"value":"/ variables and build flags as described in the module docs, and any configuration","span":{"file_name":"C:\\Users\\12935\\.cargo\\registry\\src\\mirrors.ustc.edu.cn-b63e9dae659fc205\\vcpkg-0.2.10\\src\\lib.rs","byte_start":21890,"byte_end":21974,"line_start":632,"line_end":632,"column_start":5,"column_end":89}},{"value":"/ set on the builder.","span":{"file_name":"C:\\Users\\12935\\.cargo\\registry\\src\\mirrors.ustc.edu.cn-b63e9dae659fc205\\vcpkg-0.2.10\\src\\lib.rs","byte_start":21979,"byte_end":22002,"line_start":633,"line_end":633,"column_start":5,"column_end":28}}]},{"kind":"Method","id":{"krate":0,"index":56},"span":{"file_name":"C:\\Users\\12935\\.cargo\\registry\\src\\mirrors.ustc.edu.cn-b63e9dae659fc205\\vcpkg-0.2.10\\src\\lib.rs","byte_start":28316,"byte_end":28330,"line_start":793,"line_end":793,"column_start":12,"column_end":26},"name":"cargo_metadata","qualname":"<Config>::cargo_metadata","value":"fn (&mut self, cargo_metadata: bool) -> &mut Config","parent":null,"children":[],"decl_id":null,"docs":" Define whether metadata should be emitted for cargo allowing it to\n automatically link the binary. Defaults to `true`.\n","sig":null,"attributes":[{"value":"/ Define whether metadata should be emitted for cargo allowing it to","span":{"file_name":"C:\\Users\\12935\\.cargo\\registry\\src\\mirrors.ustc.edu.cn-b63e9dae659fc205\\vcpkg-0.2.10\\src\\lib.rs","byte_start":28175,"byte_end":28245,"line_start":791,"line_end":791,"column_start":5,"column_end":75}},{"value":"/ automatically link the binary. Defaults to `true`.","span":{"file_name":"C:\\Users\\12935\\.cargo\\registry\\src\\mirrors.ustc.edu.cn-b63e9dae659fc205\\vcpkg-0.2.10\\src\\lib.rs","byte_start":28250,"byte_end":28304,"line_start":792,"line_end":792,"column_start":5,"column_end":59}}]},{"kind":"Method","id":{"krate":0,"index":57},"span":{"file_name":"C:\\Users\\12935\\.cargo\\registry\\src\\mirrors.ustc.edu.cn-b63e9dae659fc205\\vcpkg-0.2.10\\src\\lib.rs","byte_start":28537,"byte_end":28550,"line_start":799,"line_end":799,"column_start":12,"column_end":25},"name":"emit_includes","qualname":"<Config>::emit_includes","value":"fn (&mut self, emit_includes: bool) -> &mut Config","parent":null,"children":[],"decl_id":null,"docs":" Define cargo:include= metadata should be emitted. Defaults to `false`.\n","sig":null,"attributes":[{"value":"/ Define cargo:include= metadata should be emitted. Defaults to `false`.","span":{"file_name":"C:\\Users\\12935\\.cargo\\registry\\src\\mirrors.ustc.edu.cn-b63e9dae659fc205\\vcpkg-0.2.10\\src\\lib.rs","byte_start":28451,"byte_end":28525,"line_start":798,"line_end":798,"column_start":5,"column_end":79}}]},{"kind":"Method","id":{"krate":0,"index":58},"span":{"file_name":"C:\\Users\\12935\\.cargo\\registry\\src\\mirrors.ustc.edu.cn-b63e9dae659fc205\\vcpkg-0.2.10\\src\\lib.rs","byte_start":28745,"byte_end":28754,"line_start":806,"line_end":806,"column_start":12,"column_end":21},"name":"copy_dlls","qualname":"<Config>::copy_dlls","value":"fn (&mut self, copy_dlls: bool) -> &mut Config","parent":null,"children":[],"decl_id":null,"docs":" Should DLLs be copied to OUT_DIR?\n Defaults to `true`.\n","sig":null,"attributes":[{"value":"/ Should DLLs be copied to OUT_DIR?","span":{"file_name":"C:\\Users\\12935\\.cargo\\registry\\src\\mirrors.ustc.edu.cn-b63e9dae659fc205\\vcpkg-0.2.10\\src\\lib.rs","byte_start":28668,"byte_end":28705,"line_start":804,"line_end":804,"column_start":5,"column_end":42}},{"value":"/ Defaults to `true`.","span":{"file_name":"C:\\Users\\12935\\.cargo\\registry\\src\\mirrors.ustc.edu.cn-b63e9dae659fc205\\vcpkg-0.2.10\\src\\lib.rs","byte_start":28710,"byte_end":28733,"line_start":805,"line_end":805,"column_start":5,"column_end":28}}]},{"kind":"Method","id":{"krate":0,"index":59},"span":{"file_name":"C:\\Users\\12935\\.cargo\\registry\\src\\mirrors.ustc.edu.cn-b63e9dae659fc205\\vcpkg-0.2.10\\src\\lib.rs","byte_start":29048,"byte_end":29058,"line_start":813,"line_end":813,"column_start":12,"column_end":22},"name":"vcpkg_root","qualname":"<Config>::vcpkg_root","value":"fn (&mut self, vcpkg_root: PathBuf) -> &mut Config","parent":null,"children":[],"decl_id":null,"docs":" Define which path to use as vcpkg root overriding the VCPKG_ROOT environment variable\n Default to `None`, which means use VCPKG_ROOT or try to find out automatically\n","sig":null,"attributes":[{"value":"/ Define which path to use as vcpkg root overriding the VCPKG_ROOT environment variable","span":{"file_name":"C:\\Users\\12935\\.cargo\\registry\\src\\mirrors.ustc.edu.cn-b63e9dae659fc205\\vcpkg-0.2.10\\src\\lib.rs","byte_start":28860,"byte_end":28949,"line_start":811,"line_end":811,"column_start":5,"column_end":94}},{"value":"/ Default to `None`, which means use VCPKG_ROOT or try to find out automatically","span":{"file_name":"C:\\Users\\12935\\.cargo\\registry\\src\\mirrors.ustc.edu.cn-b63e9dae659fc205\\vcpkg-0.2.10\\src\\lib.rs","byte_start":28954,"byte_end":29036,"line_start":812,"line_end":812,"column_start":5,"column_end":87}}]},{"kind":"Method","id":{"krate":0,"index":60},"span":{"file_name":"C:\\Users\\12935\\.cargo\\registry\\src\\mirrors.ustc.edu.cn-b63e9dae659fc205\\vcpkg-0.2.10\\src\\lib.rs","byte_start":29424,"byte_end":29429,"line_start":824,"line_end":824,"column_start":12,"column_end":17},"name":"probe","qualname":"<Config>::probe","value":"fn (&mut self, port_name: &str) -> Result<Library, Error>","parent":null,"children":[],"decl_id":null,"docs":" Find the library `port_name` in a Vcpkg tree.","sig":null,"attributes":[{"value":"/ Find the library `port_name` in a Vcpkg tree.","span":{"file_name":"C:\\Users\\12935\\.cargo\\registry\\src\\mirrors.ustc.edu.cn-b63e9dae659fc205\\vcpkg-0.2.10\\src\\lib.rs","byte_start":29176,"byte_end":29225,"line_start":818,"line_end":818,"column_start":5,"column_end":54}},{"value":"/","span":{"file_name":"C:\\Users\\12935\\.cargo\\registry\\src\\mirrors.ustc.edu.cn-b63e9dae659fc205\\vcpkg-0.2.10\\src\\lib.rs","byte_start":29230,"byte_end":29233,"line_start":819,"line_end":819,"column_start":5,"column_end":8}},{"value":"/ This will use all configuration previously set to select the","span":{"file_name":"C:\\Users\\12935\\.cargo\\registry\\src\\mirrors.ustc.edu.cn-b63e9dae659fc205\\vcpkg-0.2.10\\src\\lib.rs","byte_start":29238,"byte_end":29302,"line_start":820,"line_end":820,"column_start":5,"column_end":69}},{"value":"/ architecture and linkage.","span":{"file_name":"C:\\Users\\12935\\.cargo\\registry\\src\\mirrors.ustc.edu.cn-b63e9dae659fc205\\vcpkg-0.2.10\\src\\lib.rs","byte_start":29307,"byte_end":29336,"line_start":821,"line_end":821,"column_start":5,"column_end":34}},{"value":"/ Deprecated in favor of the find_package function","span":{"file_name":"C:\\Users\\12935\\.cargo\\registry\\src\\mirrors.ustc.edu.cn-b63e9dae659fc205\\vcpkg-0.2.10\\src\\lib.rs","byte_start":29341,"byte_end":29393,"line_start":822,"line_end":822,"column_start":5,"column_end":57}}]},{"kind":"Method","id":{"krate":0,"index":63},"span":{"file_name":"C:\\Users\\12935\\.cargo\\registry\\src\\mirrors.ustc.edu.cn-b63e9dae659fc205\\vcpkg-0.2.10\\src\\lib.rs","byte_start":36186,"byte_end":36194,"line_start":994,"line_end":994,"column_start":12,"column_end":20},"name":"lib_name","qualname":"<Config>::lib_name","value":"fn (&mut self, lib_stem: &str) -> &mut Config","parent":null,"children":[],"decl_id":null,"docs":" Override the name of the library to look for if it differs from the package name.","sig":null,"attributes":[{"value":"/ Override the name of the library to look for if it differs from the package name.","span":{"file_name":"C:\\Users\\12935\\.cargo\\registry\\src\\mirrors.ustc.edu.cn-b63e9dae659fc205\\vcpkg-0.2.10\\src\\lib.rs","byte_start":35719,"byte_end":35804,"line_start":987,"line_end":987,"column_start":5,"column_end":90}},{"value":"/","span":{"file_name":"C:\\Users\\12935\\.cargo\\registry\\src\\mirrors.ustc.edu.cn-b63e9dae659fc205\\vcpkg-0.2.10\\src\\lib.rs","byte_start":35809,"byte_end":35812,"line_start":988,"line_end":988,"column_start":5,"column_end":8}},{"value":"/ This may be called more than once if multiple libs are required.","span":{"file_name":"C:\\Users\\12935\\.cargo\\registry\\src\\mirrors.ustc.edu.cn-b63e9dae659fc205\\vcpkg-0.2.10\\src\\lib.rs","byte_start":35817,"byte_end":35885,"line_start":989,"line_end":989,"column_start":5,"column_end":73}},{"value":"/ All libs must be found for the probe to succeed. `.probe()` must","span":{"file_name":"C:\\Users\\12935\\.cargo\\registry\\src\\mirrors.ustc.edu.cn-b63e9dae659fc205\\vcpkg-0.2.10\\src\\lib.rs","byte_start":35890,"byte_end":35958,"line_start":990,"line_end":990,"column_start":5,"column_end":73}},{"value":"/ be run with a different configuration to look for libraries under one of several names.","span":{"file_name":"C:\\Users\\12935\\.cargo\\registry\\src\\mirrors.ustc.edu.cn-b63e9dae659fc205\\vcpkg-0.2.10\\src\\lib.rs","byte_start":35963,"byte_end":36054,"line_start":991,"line_end":991,"column_start":5,"column_end":96}},{"value":"/ `.libname(\"ssleay32\")` will look for ssleay32.lib and also ssleay32.dll if","span":{"file_name":"C:\\Users\\12935\\.cargo\\registry\\src\\mirrors.ustc.edu.cn-b63e9dae659fc205\\vcpkg-0.2.10\\src\\lib.rs","byte_start":36059,"byte_end":36137,"line_start":992,"line_end":992,"column_start":5,"column_end":83}},{"value":"/ dynamic linking is selected.","span":{"file_name":"C:\\Users\\12935\\.cargo\\registry\\src\\mirrors.ustc.edu.cn-b63e9dae659fc205\\vcpkg-0.2.10\\src\\lib.rs","byte_start":36142,"byte_end":36174,"line_start":993,"line_end":993,"column_start":5,"column_end":37}}]},{"kind":"Method","id":{"krate":0,"index":64},"span":{"file_name":"C:\\Users\\12935\\.cargo\\registry\\src\\mirrors.ustc.edu.cn-b63e9dae659fc205\\vcpkg-0.2.10\\src\\lib.rs","byte_start":36849,"byte_end":36858,"line_start":1007,"line_end":1007,"column_start":12,"column_end":21},"name":"lib_names","qualname":"<Config>::lib_names","value":"fn (&mut self, lib_stem: &str, dll_stem: &str) -> &mut Config","parent":null,"children":[],"decl_id":null,"docs":" Override the name of the library to look for if it differs from the package name.","sig":null,"attributes":[{"value":"/ Override the name of the library to look for if it differs from the package name.","span":{"file_name":"C:\\Users\\12935\\.cargo\\registry\\src\\mirrors.ustc.edu.cn-b63e9dae659fc205\\vcpkg-0.2.10\\src\\lib.rs","byte_start":36371,"byte_end":36456,"line_start":1000,"line_end":1000,"column_start":5,"column_end":90}},{"value":"/","span":{"file_name":"C:\\Users\\12935\\.cargo\\registry\\src\\mirrors.ustc.edu.cn-b63e9dae659fc205\\vcpkg-0.2.10\\src\\lib.rs","byte_start":36461,"byte_end":36464,"line_start":1001,"line_end":1001,"column_start":5,"column_end":8}},{"value":"/ This may be called more than once if multiple libs are required.","span":{"file_name":"C:\\Users\\12935\\.cargo\\registry\\src\\mirrors.ustc.edu.cn-b63e9dae659fc205\\vcpkg-0.2.10\\src\\lib.rs","byte_start":36469,"byte_end":36537,"line_start":1002,"line_end":1002,"column_start":5,"column_end":73}},{"value":"/ All libs must be found for the probe to succeed. `.probe()` must","span":{"file_name":"C:\\Users\\12935\\.cargo\\registry\\src\\mirrors.ustc.edu.cn-b63e9dae659fc205\\vcpkg-0.2.10\\src\\lib.rs","byte_start":36542,"byte_end":36610,"line_start":1003,"line_end":1003,"column_start":5,"column_end":73}},{"value":"/ be run with a different configuration to look for libraries under one of several names.","span":{"file_name":"C:\\Users\\12935\\.cargo\\registry\\src\\mirrors.ustc.edu.cn-b63e9dae659fc205\\vcpkg-0.2.10\\src\\lib.rs","byte_start":36615,"byte_end":36706,"line_start":1004,"line_end":1004,"column_start":5,"column_end":96}},{"value":"/ `.lib_names(\"libcurl_imp\",\"curl\")` will look for libcurl_imp.lib and also curl.dll if","span":{"file_name":"C:\\Users\\12935\\.cargo\\registry\\src\\mirrors.ustc.edu.cn-b63e9dae659fc205\\vcpkg-0.2.10\\src\\lib.rs","byte_start":36711,"byte_end":36800,"line_start":1005,"line_end":1005,"column_start":5,"column_end":94}},{"value":"/ dynamic linking is selected.","span":{"file_name":"C:\\Users\\12935\\.cargo\\registry\\src\\mirrors.ustc.edu.cn-b63e9dae659fc205\\vcpkg-0.2.10\\src\\lib.rs","byte_start":36805,"byte_end":36837,"line_start":1006,"line_end":1006,"column_start":5,"column_end":37}}]}],"impls":[{"id":0,"kind":"Direct","span":{"file_name":"C:\\Users\\12935\\.cargo\\registry\\src\\mirrors.ustc.edu.cn-b63e9dae659fc205\\vcpkg-0.2.10\\src\\lib.rs","byte_start":6002,"byte_end":6007,"line_start":178,"line_end":178,"column_start":23,"column_end":28},"value":"","parent":null,"children":[{"krate":0,"index":24},{"krate":0,"index":25}],"docs":"","sig":null,"attributes":[]},{"id":1,"kind":"Direct","span":{"file_name":"C:\\Users\\12935\\.cargo\\registry\\src\\mirrors.ustc.edu.cn-b63e9dae659fc205\\vcpkg-0.2.10\\src\\lib.rs","byte_start":6820,"byte_end":6825,"line_start":199,"line_end":199,"column_start":23,"column_end":28},"value":"","parent":null,"children":[{"krate":0,"index":27}],"docs":"","sig":null,"attributes":[]},{"id":2,"kind":"Inherent","span":{"file_name":"C:\\Users\\12935\\.cargo\\registry\\src\\mirrors.ustc.edu.cn-b63e9dae659fc205\\vcpkg-0.2.10\\src\\lib.rs","byte_start":21039,"byte_end":21050,"line_start":604,"line_end":604,"column_start":6,"column_end":17},"value":"","parent":null,"children":[{"krate":0,"index":48}],"docs":"","sig":null,"attributes":[]},{"id":3,"kind":"Inherent","span":{"file_name":"C:\\Users\\12935\\.cargo\\registry\\src\\mirrors.ustc.edu.cn-b63e9dae659fc205\\vcpkg-0.2.10\\src\\lib.rs","byte_start":21421,"byte_end":21427,"line_start":617,"line_end":617,"column_start":6,"column_end":12},"value":"","parent":null,"children":[{"krate":0,"index":52},{"krate":0,"index":53},{"krate":0,"index":56},{"krate":0,"index":57},{"krate":0,"index":58},{"krate":0,"index":59},{"krate":0,"index":60},{"krate":0,"index":61},{"krate":0,"index":62},{"krate":0,"index":63},{"krate":0,"index":64}],"docs":"","sig":null,"attributes":[]},{"id":4,"kind":"Inherent","span":{"file_name":"C:\\Users\\12935\\.cargo\\registry\\src\\mirrors.ustc.edu.cn-b63e9dae659fc205\\vcpkg-0.2.10\\src\\lib.rs","byte_start":37254,"byte_end":37261,"line_start":1021,"line_end":1021,"column_start":6,"column_end":13},"value":"","parent":null,"children":[{"krate":0,"index":68}],"docs":"","sig":null,"attributes":[]}],"refs":[],"macro_refs":[],"relations":[{"span":{"file_name":"C:\\Users\\12935\\.cargo\\registry\\src\\mirrors.ustc.edu.cn-b63e9dae659fc205\\vcpkg-0.2.10\\src\\lib.rs","byte_start":6002,"byte_end":6007,"line_start":178,"line_end":178,"column_start":23,"column_end":28},"kind":{"Impl":{"id":0}},"from":{"krate":0,"index":94},"to":{"krate":1,"index":1620}},{"span":{"file_name":"C:\\Users\\12935\\.cargo\\registry\\src\\mirrors.ustc.edu.cn-b63e9dae659fc205\\vcpkg-0.2.10\\src\\lib.rs","byte_start":6820,"byte_end":6825,"line_start":199,"line_end":199,"column_start":23,"column_end":28},"kind":{"Impl":{"id":1}},"from":{"krate":0,"index":94},"to":{"krate":2,"index":5928}},{"span":{"file_name":"C:\\Users\\12935\\.cargo\\registry\\src\\mirrors.ustc.edu.cn-b63e9dae659fc205\\vcpkg-0.2.10\\src\\lib.rs","byte_start":21039,"byte_end":21050,"line_start":604,"line_end":604,"column_start":6,"column_end":17},"kind":{"Impl":{"id":2}},"from":{"krate":0,"index":38},"to":{"krate":4294967295,"index":4294967295}},{"span":{"file_name":"C:\\Users\\12935\\.cargo\\registry\\src\\mirrors.ustc.edu.cn-b63e9dae659fc205\\vcpkg-0.2.10\\src\\lib.rs","byte_start":21421,"byte_end":21427,"line_start":617,"line_end":617,"column_start":6,"column_end":12},"kind":{"Impl":{"id":3}},"from":{"krate":0,"index":73},"to":{"krate":4294967295,"index":4294967295}},{"span":{"file_name":"C:\\Users\\12935\\.cargo\\registry\\src\\mirrors.ustc.edu.cn-b63e9dae659fc205\\vcpkg-0.2.10\\src\\lib.rs","byte_start":37254,"byte_end":37261,"line_start":1021,"line_end":1021,"column_start":6,"column_end":13},"kind":{"Impl":{"id":4}},"from":{"krate":0,"index":82},"to":{"krate":4294967295,"index":4294967295}}]}